{"metadata": {"tag": "VeChain", "tag_number": 0, "doc_number": 419, "operation_id": "vetgetenergy", "doc_url": "https://apidoc.tatum.io/tag/VeChain#operation/vetgetenergy", "server_url": "https://api.tatum.io/v3/vet/account/energy/{address}"}, "content": "path /v3/vet/account/energy/address\noperationId VetGetEnergy\nparameters\ndescription Account address you want to get balance of\nin path\nname address\nrequired True\nschema\ntype string\nsummary Get VeChain Account energy VTHO\ndescription 5 credits per API callGet VeChain Account energy in VTHO VTHO is used for paying for the transaction fee\nresponses\n200\nschema\ntype object\nenergy\ntype string\ndescription Balance in VTHO\ndescription OK"}