{
    "tag": "Monitors",
    "content": "this is a single endpoint from an open api spec document\nit has been minified by removing unnecessary kvps\nadditionally common terms have been abbreviated  operationId: Enable path: https://gateway.stackpath.com/monitoring/v2/stacks/{stack_id}/enable content: params\nname stackid\ndesc a stack id or slug\nin path\nrequired true\nschema\ntype str\nsum enable all monitors\nresponses",
    "operation_id": "Enable",
    "doc_url": "https://stackpath.dev/reference/Enable",
    "server_url": "https://gateway.stackpath.com/monitoring/v2/stacks/{stack_id}/enable",
    "tag_summary": "",
    "tag_number": 14,
    "doc_number": 78,
    "title": "14_Monitors_Enable_78.json"
}