{
    "tag": "SSL",
    "content": "this is a single endpoint from an open api spec document\nit has been minified by removing unnecessary kvps\nadditionally common terms have been abbreviated  operationId: GetCertificateVerificationDetails path: https://gateway.stackpath.com/cdn/v1/stacks/{stack_id}/certificates/{certificate_id}/verification_details content: params\nname stackid\ndesc a stack id or slug\nin path\nrequired true\nschema\ntype str\nname certificateid\ndesc a certificate id\nin path\nrequired true\nschema\ntype str\nsum get verification details\nresponses\n200\ncdngetcertificateverificationdetailsresponse\ntype obj\nprops\nmanualverificationrequired\ntype bool\nformat bool\ndesc whether or not the end user must provide their own certificate verification\nverificationrequirements\ntype arr\ncdnverificationrequirements\ntype obj\nprops\ncdndnsverificationdetails\ntype obj\nprops\ndnsrecords\ntype str\ndesc a list of dns records that will validate domain ownership\nrecords\ntype arr\ncdndnsrecord\ntype obj\nprops\nname\ntype str\ndesc the name of the network node to which a zone resource record pertains\n\nuse the value  to denote current root domain name\ntype\ntype str\ndesc a zone records type\n\nzone record types describe the zone records behavior for instance a zone records type can say that the record is a name to ip address value a name alias or which mail exchanger is responsible for the domain see https//supportstackpathcom/hc/enus/articles/360001085563whatdnsrecordtypesdoesstackpathsupport for more information\nclass\ntype str\ndesc a zone records class code\n\nthis is typically in for internet related resource records\nttl\ntype integer\nformat int32\ndesc a zone records time to live\n\na records ttl is the number of seconds that the record should be cached by dns resolvers use lower ttl values if you expect zone records to change often use higher ttl values for records that wont change to prevent extra dns lookups by clients\ndata\ntype str\ndesc a zone records value\n\nexpected data formats can vary depending on the zone records type\ndesc a dns record\n\na dns record describes an individual piece of dns functionality in a dns zone\ndesc a list of parsed dns records required for ssl verification\ndesc dnsbased domain ownership verification details\ncdnhttpverificationdetails\ntype obj\nprops\npath\ntype str\ndesc path to the verification file\ncontenttype\ntype str\ndesc response content type\nbody\ntype str\ndesc body content of response\ndesc httpbased domain ownership verification details\ncdncertificateverificationmethod\ntype str\ndefault dns\ndesc the certificate verification method\n\nverification method used to validate a requested certificate on a site\n\n  dns verify a certificate using dns records\n  http verify a certificate by using http validation this will require all hosts in the certificate point to the sites stackpathcdncom delivery domain or ip address\ndesc conditions that must be met to verify ownership of a domain for ssl certificate provisioning\ndesc an ssl certificates verification requirements\ncertificatecertificatestatusdetails\ntype obj\nverificationfailures\ntype arr\ncertificatecertificateverificationfailure\ntype obj\nprops\ndomain\ntype str\ndesc the host the verification failed on\ndetails\ntype str\ndesc detailed information about the failure\ncheckedat\ntype str\nformat datetime\ndesc the last time the failure was detected\ndesc a record that indicates why a domain is failing ssl validation\ndesc failures preventing the certificate from being issued\ndesc detailed certificate status\ndesc the response from a request to retrieve an ssl certificates manual verification details",
    "operation_id": "GetCertificateVerificationDetails",
    "doc_url": "https://stackpath.dev/reference/GetCertificateVerificationDetails",
    "server_url": "https://gateway.stackpath.com/cdn/v1/stacks/{stack_id}/certificates/{certificate_id}/verification_details",
    "tag_summary": "",
    "tag_number": 23,
    "doc_number": 135,
    "title": "23_SSL_GetCertificateVerificationDetails_135.json"
}