{"metadata": {"tag": "Resource Records", "tag_number": 0, "doc_number": 118, "operation_id": "patchzonerecord", "doc_url": "https://stackpath.dev/reference/patchzonerecord", "server_url": "https://gateway.stackpath.com/dns/v1/stacks/{stack_id}/zones/{zone_id}/records/{zone_record_id}"}, "content": "path /dns/v1/stacks/stackid/zones/zoneid/records/zonerecordid\noperationId PatchZoneRecord\nparameters\nname stackid\ndescription A stack ID or slug\nin path\nrequired True\nschema\ntype string\nname zoneid\ndescription A DNS zone ID\nin path\nrequired True\nschema\ntype string\nname zonerecordid\ndescription A DNS resource record ID\nin path\nrequired True\nschema\ntype string\nsummary Replace a record\nrequestBody\nzonePatchZoneRecordMessage\ntype object\nproperties\nname\ntype string\ndescription A zone records name\nzoneRecordType\ntype string\ndefault EMPTY\ndescription The resource record types supported by StackPath\n\n EMPTY The resource record has no type\n  A The resource record translates a host to an IPv4 address\n  AAAA The resource record translates a host to an IPv6 address\n  CNAME The resource record aliases one name to another\n  TXT The resource record contains a descriptive string Many applications use TXT records for configuration\n  MX The resource record defines a mail exchanger for the given host\n  SRV The resource record defines a service on the domain\n  NS The resource record describes a nameserver that serves its domains zone and records\n  CAA The resource record describes a certification authority authorization that adds validation to which certificate authorities can issue certificates for a domain\nttl\ntype integer\nformat int32\ndescription A zone records time to live\n\nA records TTL is the number of seconds that the record should be cached by DNS resolvers Use lower TTL values if you expect zone records to change often Use higher TTL values for records that wont change to prevent extra DNS lookups by clients\ndata\ntype string\ndescription A zone records value\n\nMX record data follows the format   without s\nweight\ntype integer\nformat int32\ndescription A zone records priority\n\nA resource record is replicated in StackPaths DNS infrastructure the number of times of the records weight giving it a more likely response to queries if a zone has records with the same name and type\nrequired True\nresponses\n200\nzoneUpdateZoneRecordResponse\ntype object\nzoneZoneRecord\ntype object\nproperties\nid\ntype string\ndescription A zone records unique ID\nzoneId\ntype string\ndescription The ID of the zone that a zone record belongs to\nname\ntype string\ndescription A zone records name\n\nUse the value  to denote current root domain name\ntype\ntype string\ndescription A zone records type\n\nZone record types describe the zone records behavior For instance a zone records type can say that the record is a name to IP address value a name alias or which mail exchanger is responsible for the domain See https//supportstackpathcom/hc/enus/articles/360001085563WhatDNSrecordtypesdoesStackPathsupport for more information\nclass\ntype string\ndescription A zone records class code\n\nThis is typically IN for Internet related resource records\nttl\ntype integer\nformat int32\ndescription A zone records time to live\n\nA records TTL is the number of seconds that the record should be cached by DNS resolvers Use lower TTL values if you expect zone records to change often Use higher TTL values for records that wont change to prevent extra DNS lookups by clients\ndata\ntype string\ndescription A zone records value\n\nMX record data follows the format   without s\nweight\ntype integer\nformat int32\ndescription A zone records priority\n\nA resource record is replicated in StackPaths DNS infrastructure the number of times of the records weight giving it a more likely response to queries if a zone has records with the same name and type\nlabels\ntype string\ndescription A key/value pair of userdefined labels for a zone record\n\nZone record labels are not processed by StackPath and are solely used for users to organize their DNS zones\ncreated\ntype string\nformat datetime\ndescription The date a zone record was created\nupdated\ntype string\nformat datetime\ndescription The date a zone record was last updated\ndescription A DNS zones resource record\n\nA zone record describes an individual piece of DNS functionality in a DNS zone\ndescription A response from a request to replace a DNS zone resource record"}